["{\"type\":\"list\",\"attributes\":{\"names\":{\"type\":\"character\",\"attributes\":{},\"value\":[\"coef\",\"sigma2\",\"var.coef\",\"mask\",\"loglik\",\"aic\",\"arma\",\"residuals\",\"call\",\"series\",\"code\",\"n.cond\",\"nobs\",\"model\",\"bic\",\"aicc\",\"x\",\"fitted\"]},\"class\":{\"type\":\"character\",\"attributes\":{},\"value\":[\"forecast_ARIMA\",\"ARIMA\",\"Arima\"]}},\"value\":[{\"type\":\"double\",\"attributes\":{\"names\":{\"type\":\"character\",\"attributes\":{},\"value\":[\"ar1\"]}},\"value\":[-0.51528327]},{\"type\":\"double\",\"attributes\":{},\"value\":[1.51416253]},{\"type\":\"double\",\"attributes\":{\"dim\":{\"type\":\"integer\",\"attributes\":{},\"value\":[1,1]},\"dimnames\":{\"type\":\"list\",\"attributes\":{},\"value\":[{\"type\":\"character\",\"attributes\":{},\"value\":[\"ar1\"]},{\"type\":\"character\",\"attributes\":{},\"value\":[\"ar1\"]}]}},\"value\":[0.00249236]},{\"type\":\"logical\",\"attributes\":{},\"value\":[true]},{\"type\":\"double\",\"attributes\":{},\"value\":[-458.89096142]},{\"type\":\"double\",\"attributes\":{},\"value\":[921.78192283]},{\"type\":\"integer\",\"attributes\":{},\"value\":[1,0,0,0,1,1,0]},{\"type\":\"double\",\"attributes\":{\"tsp\":{\"type\":\"double\",\"attributes\":{},\"value\":[1,354,1]},\"class\":{\"type\":\"character\",\"attributes\":{},\"value\":[\"ts\"]}},\"value\":[0,0,1,1.51528327,-0.48471673,-1.51528327,0.48471673,2.51528327,0.03056655,5.48471673,6.09169964,-3.45415018,-3.57641636,-0.51528327,2,-4.96943345,3.90830036,-2.39301709,1.90830036,1.57641636,-4.51528327,2.93886691,1.57641636,0.48471673,-4.48471673,\"NA\",0.67594642,1.40714899,0.03056655,-2.51528327,-0.03056655,1.51528327,-0.48471673,\"NA\",-1.12461562,-2.29347996,-2.03056655,-0.51528327,1.14415871e-16,0,\"NA\",0,0,0,0,1,-0.48471673,-0.51528327,0,0,0,\"NA\",0,0,0,0,\"NA\",\"NA\",0,0,0,0,0,0,\"NA\",\"NA\",0,0,0,\"NA\",0,0,\"NA\",0,0,\"NA\",\"NA\",0.74581175,0.2462089,0,\"NA\",\"NA\",0.74581175,-0.65855409,3.48471673,-2.93886691,\"NA\",\"NA\",-1.44159003,1.65255066,1.03056655,-1,-1.51528327,0.48471673,\"NA\",-0.67510567,0.81828033,0.51528327,0,-1,-0.51528327,2,-0.96943345,-1.03056655,3,-0.45415018,-0.03056655,-0.48471673,-0.51528327,-1,-0.51528327,0,0,0,0,\"NA\",0,\"NA\",\"NA\",0,0,0,\"NA\",0,0,\"NA\",\"NA\",0,\"NA\",0,0,0,0,1,2.51528327,-1.96943345,-1.54584982,0,1,2.51528327,-0.96943345,-1.03056655,\"NA\",0,\"NA\",-0.88200258,-0.24963501,0,0,\"NA\",0,1.81443531,-0.96943345,-0.03056655,-0.48471673,0.48471673,\"NA\",2.02447627,-0.14418203,2.48471673,-3.45415018,-2.57641636,0,0,0,3,1.54584982,2,-2.96943345,-3.06113309,0.48471673,-0.48471673,0.48471673,-0.48471673,-0.51528327,0,0,0,0,0,0,0,0,0,0,0,0,0,0,0,0,\"NA\",0,\"NA\",0,\"NA\",0.87911824,\"NA\",-0.76204526,-0.14626437,-2.86039677e-17,1,0.51528327,\"NA\",-0.89986065,-0.28399099,5.72079354e-17,0,1,\"NA\",\"NA\",0.28831801,1.84092105,2.03056655,-2.48471673,\"NA\",-0.67426492,-1.49237863,1.48471673,-0.96943345,-1.03056655,0,0,0,0,2,-0.96943345,-1.03056655,\"NA\",0.89986065,\"NA\",-0.74817337,\"NA\",-0.06550649,\"NA\",-0.02607346,-0.02171723,3.57549596e-18,0,0,0,0,0,0,0,0,0,\"NA\",0,0.90721766,-0.48471673,-0.51528327,0,1,-0.48471673,-0.51528327,0,0,0,\"NA\",\"NA\",0,0,\"NA\",0,0,0,0,0,0,0,\"NA\",\"NA\",0,0,0,0,0,0,\"NA\",0,0,0,0,\"NA\",\"NA\",\"NA\",0,0,0,0,0,0,0,0,0,\"NA\",\"NA\",\"NA\",0,0,0,0,0,0,0,0,0,0,0,0,\"NA\",\"NA\",\"NA\",\"NA\",\"NA\",\"NA\",\"NA\",\"NA\",\"NA\",\"NA\",\"NA\",\"NA\",\"NA\",\"NA\",\"NA\",\"NA\",0,\"NA\",\"NA\",\"NA\",0,0,0,0,0,0,0,\"NA\",\"NA\",0,0,0,0,0,\"NA\",0,0,0,0,0,\"NA\",\"NA\",\"NA\"]},{\"type\":\"language\",\"attributes\":{},\"value\":[\"auto.arima(y = c(0L, 0L, 1L, 2L, 1L, 0L, 1L, 3L, 2L, 8L, 11L, \",\"6L, 5L, 5L, 7L, 1L, 8L, 2L, 7L, 6L, 2L, 7L, 6L, 7L, 2L, NA, 4L, \",\"6L, 5L, 3L, 4L, 5L, 4L, NA, 3L, 1L, 0L, 0L, 0L, 0L, NA, 0L, 0L, \",\"0L, 0L, 1L, 0L, 0L, 0L, 0L, 0L, NA, 0L, 0L, 0L, 0L, NA, NA, 0L, \",\"0L, 0L, 0L, 0L, 0L, NA, NA, 0L, 0L, 0L, NA, 0L, 0L, NA, 0L, 0L, \",\"NA, NA, 1L, 1L, 1L, NA, NA, 2L, 1L, 5L, 0L, NA, NA, 0L, 2L, 2L, \",\"1L, 0L, 1L, NA, 0L, 1L, 1L, 1L, 0L, 0L, 2L, 0L, 0L, 3L, 1L, 2L, \",\"1L, 1L, 0L, 0L, 0L, 0L, 0L, 0L, NA, 0L, NA, NA, 0L, 0L, 0L, NA, \",\"0L, 0L, NA, NA, 0L, NA, 0L, 0L, 0L, 0L, 1L, 3L, 0L, 0L, 0L, 1L, \",\"3L, 1L, 1L, NA, 1L, NA, 0L, 0L, 0L, 0L, NA, 0L, 2L, 0L, 1L, 0L, \",\"1L, NA, 3L, 2L, 5L, 0L, 0L, 0L, 0L, 0L, 3L, 3L, 5L, 1L, 0L, 1L, \",\"0L, 1L, 0L, 0L, 0L, 0L, 0L, 0L, 0L, 0L, 0L, 0L, 0L, 0L, 0L, 0L, \",\"0L, 0L, 0L, 0L, NA, 0L, NA, 0L, NA, 1L, NA, 0L, 0L, 0L, 1L, 1L, \",\"NA, 0L, 0L, 0L, 0L, 1L, NA, NA, 1L, 3L, 4L, 1L, NA, 1L, 0L, 2L, \",\"0L, 0L, 0L, 0L, 0L, 0L, 2L, 0L, 0L, NA, 1L, NA, 0L, NA, 0L, NA, \",\"0L, 0L, 0L, 0L, 0L, 0L, 0L, 0L, 0L, 0L, 0L, 0L, NA, 0L, 1L, 0L, \",\"0L, 0L, 1L, 0L, 0L, 0L, 0L, 0L, NA, NA, 0L, 0L, NA, 0L, 0L, 0L, \",\"0L, 0L, 0L, 0L, NA, NA, 0L, 0L, 0L, 0L, 0L, 0L, NA, 0L, 0L, 0L, \",\"0L, NA, NA, NA, 0L, 0L, 0L, 0L, 0L, 0L, 0L, 0L, 0L, NA, NA, NA, \",\"0L, 0L, 0L, 0L, 0L, 0L, 0L, 0L, 0L, 0L, 0L, 0L, NA, NA, NA, NA, \",\"NA, NA, NA, NA, NA, NA, NA, NA, NA, NA, NA, NA, 0L, NA, NA, NA, \",\"0L, 0L, 0L, 0L, 0L, 0L, 0L, NA, NA, 0L, 0L, 0L, 0L, 0L, NA, 0L, \",\"0L, 0L, 0L, 0L, NA, NA, NA), x = structure(list(x = structure(c(0L, \",\"0L, 1L, 2L, 1L, 0L, 1L, 3L, 2L, 8L, 11L, 6L, 5L, 5L, 7L, 1L, \",\"8L, 2L, 7L, 6L, 2L, 7L, 6L, 7L, 2L, NA, 4L, 6L, 5L, 3L, 4L, 5L, \",\"4L, NA, 3L, 1L, 0L, 0L, 0L, 0L, NA, 0L, 0L, 0L, 0L, 1L, 0L, 0L, \",\"0L, 0L, 0L, NA, 0L, 0L, 0L, 0L, NA, NA, 0L, 0L, 0L, 0L, 0L, 0L, \",\"NA, NA, 0L, 0L, 0L, NA, 0L, 0L, NA, 0L, 0L, NA, NA, 1L, 1L, 1L, \",\"NA, NA, 2L, 1L, 5L, 0L, NA, NA, 0L, 2L, 2L, 1L, 0L, 1L, NA, 0L, \",\"1L, 1L, 1L, 0L, 0L, 2L, 0L, 0L, 3L, 1L, 2L, 1L, 1L, 0L, 0L, 0L, \",\"0L, 0L, 0L, NA, 0L, NA, NA, 0L, 0L, 0L, NA, 0L, 0L, NA, NA, 0L, \",\"NA, 0L, 0L, 0L, 0L, 1L, 3L, 0L, 0L, 0L, 1L, 3L, 1L, 1L, NA, 1L, \",\"NA, 0L, 0L, 0L, 0L, NA, 0L, 2L, 0L, 1L, 0L, 1L, NA, 3L, 2L, 5L, \",\"0L, 0L, 0L, 0L, 0L, 3L, 3L, 5L, 1L, 0L, 1L, 0L, 1L, 0L, 0L, 0L, \",\"0L, 0L, 0L, 0L, 0L, 0L, 0L, 0L, 0L, 0L, 0L, 0L, 0L, 0L, 0L, NA, \",\"0L, NA, 0L, NA, 1L, NA, 0L, 0L, 0L, 1L, 1L, NA, 0L, 0L, 0L, 0L, \",\"1L, NA, NA, 1L, 3L, 4L, 1L, NA, 1L, 0L, 2L, 0L, 0L, 0L, 0L, 0L, \",\"0L, 2L, 0L, 0L, NA, 1L, NA, 0L, NA, 0L, NA, 0L, 0L, 0L, 0L, 0L, \",\"0L, 0L, 0L, 0L, 0L, 0L, 0L, NA, 0L, 1L, 0L, 0L, 0L, 1L, 0L, 0L, \",\"0L, 0L, 0L, NA, NA, 0L, 0L, NA, 0L, 0L, 0L, 0L, 0L, 0L, 0L, NA, \",\"NA, 0L, 0L, 0L, 0L, 0L, 0L, NA, 0L, 0L, 0L, 0L, NA, NA, NA, 0L, \",\"0L, 0L, 0L, 0L, 0L, 0L, 0L, 0L, NA, NA, NA, 0L, 0L, 0L, 0L, 0L, \",\"0L, 0L, 0L, 0L, 0L, 0L, 0L, NA, NA, NA, NA, NA, NA, NA, NA, NA, \",\"NA, NA, NA, NA, NA, NA, NA, 0L, NA, NA, NA, 0L, 0L, 0L, 0L, 0L, \",\"0L, 0L, NA, NA, 0L, 0L, 0L, 0L, 0L, NA, 0L, 0L, 0L, 0L, 0L, NA, \",\"NA, NA), tsp = c(1, 354, 1), class = \\\"ts\\\")), class = \\\"data.frame\\\", row.names = c(NA, \",\"-354L)))\"]},{\"type\":\"character\",\"attributes\":{},\"value\":[\"c(0L, 0L, 1L, 2L, 1L, 0L, 1L, 3L, 2L, 8L, 11L, 6L, 5L, 5L, 7L, \",\"1L, 8L, 2L, 7L, 6L, 2L, 7L, 6L, 7L, 2L, NA, 4L, 6L, 5L, 3L, 4L, \",\"5L, 4L, NA, 3L, 1L, 0L, 0L, 0L, 0L, NA, 0L, 0L, 0L, 0L, 1L, 0L, \",\"0L, 0L, 0L, 0L, NA, 0L, 0L, 0L, 0L, NA, NA, 0L, 0L, 0L, 0L, 0L, \",\"0L, NA, NA, 0L, 0L, 0L, NA, 0L, 0L, NA, 0L, 0L, NA, NA, 1L, 1L, \",\"1L, NA, NA, 2L, 1L, 5L, 0L, NA, NA, 0L, 2L, 2L, 1L, 0L, 1L, NA, \",\"0L, 1L, 1L, 1L, 0L, 0L, 2L, 0L, 0L, 3L, 1L, 2L, 1L, 1L, 0L, 0L, \",\"0L, 0L, 0L, 0L, NA, 0L, NA, NA, 0L, 0L, 0L, NA, 0L, 0L, NA, NA, \",\"0L, NA, 0L, 0L, 0L, 0L, 1L, 3L, 0L, 0L, 0L, 1L, 3L, 1L, 1L, NA, \",\"1L, NA, 0L, 0L, 0L, 0L, NA, 0L, 2L, 0L, 1L, 0L, 1L, NA, 3L, 2L, \",\"5L, 0L, 0L, 0L, 0L, 0L, 3L, 3L, 5L, 1L, 0L, 1L, 0L, 1L, 0L, 0L, \",\"0L, 0L, 0L, 0L, 0L, 0L, 0L, 0L, 0L, 0L, 0L, 0L, 0L, 0L, 0L, 0L, \",\"NA, 0L, NA, 0L, NA, 1L, NA, 0L, 0L, 0L, 1L, 1L, NA, 0L, 0L, 0L, \",\"0L, 1L, NA, NA, 1L, 3L, 4L, 1L, NA, 1L, 0L, 2L, 0L, 0L, 0L, 0L, \",\"0L, 0L, 2L, 0L, 0L, NA, 1L, NA, 0L, NA, 0L, NA, 0L, 0L, 0L, 0L, \",\"0L, 0L, 0L, 0L, 0L, 0L, 0L, 0L, NA, 0L, 1L, 0L, 0L, 0L, 1L, 0L, \",\"0L, 0L, 0L, 0L, NA, NA, 0L, 0L, NA, 0L, 0L, 0L, 0L, 0L, 0L, 0L, \",\"NA, NA, 0L, 0L, 0L, 0L, 0L, 0L, NA, 0L, 0L, 0L, 0L, NA, NA, NA, \",\"0L, 0L, 0L, 0L, 0L, 0L, 0L, 0L, 0L, NA, NA, NA, 0L, 0L, 0L, 0L, \",\"0L, 0L, 0L, 0L, 0L, 0L, 0L, 0L, NA, NA, NA, NA, NA, NA, NA, NA, \",\"NA, NA, NA, NA, NA, NA, NA, NA, 0L, NA, NA, NA, 0L, 0L, 0L, 0L, \",\"0L, 0L, 0L, NA, NA, 0L, 0L, 0L, 0L, 0L, NA, 0L, 0L, 0L, 0L, 0L, \",\"NA, NA, NA)\"]},{\"type\":\"integer\",\"attributes\":{},\"value\":[0]},{\"type\":\"double\",\"attributes\":{},\"value\":[0]},{\"type\":\"integer\",\"attributes\":{},\"value\":[275]},{\"type\":\"list\",\"attributes\":{\"names\":{\"type\":\"character\",\"attributes\":{},\"value\":[\"phi\",\"theta\",\"Delta\",\"Z\",\"a\",\"P\",\"T\",\"V\",\"h\",\"Pn\"]}},\"value\":[{\"type\":\"double\",\"attributes\":{},\"value\":[-0.51528327]},{\"type\":\"double\",\"attributes\":{},\"value\":[]},{\"type\":\"double\",\"attributes\":{},\"value\":[1]},{\"type\":\"double\",\"attributes\":{},\"value\":[1,1]},{\"type\":\"double\",\"attributes\":{},\"value\":[0,0]},{\"type\":\"double\",\"attributes\":{\"dim\":{\"type\":\"integer\",\"attributes\":{},\"value\":[2,2]}},\"value\":[1.33601605,-0.38658281,-0.38658281,1.23495031]},{\"type\":\"double\",\"attributes\":{\"dim\":{\"type\":\"integer\",\"attributes\":{},\"value\":[2,2]}},\"value\":[-0.51528327,1,0,1]},{\"type\":\"double\",\"attributes\":{\"dim\":{\"type\":\"integer\",\"attributes\":{},\"value\":[2,2]}},\"value\":[1,0,0,0]},{\"type\":\"double\",\"attributes\":{},\"value\":[0]},{\"type\":\"double\",\"attributes\":{\"dim\":{\"type\":\"integer\",\"attributes\":{},\"value\":[2,2]}},\"value\":[1.33601605,-0.38658281,-0.38658281,1.23495031]}]},{\"type\":\"double\",\"attributes\":{},\"value\":[929.01546503]},{\"type\":\"double\",\"attributes\":{},\"value\":[921.82604048]},{\"type\":\"integer\",\"attributes\":{\"tsp\":{\"type\":\"double\",\"attributes\":{},\"value\":[1,354,1]},\"class\":{\"type\":\"character\",\"attributes\":{},\"value\":[\"ts\"]}},\"value\":[0,0,1,2,1,0,1,3,2,8,11,6,5,5,7,1,8,2,7,6,2,7,6,7,2,\"NA\",4,6,5,3,4,5,4,\"NA\",3,1,0,0,0,0,\"NA\",0,0,0,0,1,0,0,0,0,0,\"NA\",0,0,0,0,\"NA\",\"NA\",0,0,0,0,0,0,\"NA\",\"NA\",0,0,0,\"NA\",0,0,\"NA\",0,0,\"NA\",\"NA\",1,1,1,\"NA\",\"NA\",2,1,5,0,\"NA\",\"NA\",0,2,2,1,0,1,\"NA\",0,1,1,1,0,0,2,0,0,3,1,2,1,1,0,0,0,0,0,0,\"NA\",0,\"NA\",\"NA\",0,0,0,\"NA\",0,0,\"NA\",\"NA\",0,\"NA\",0,0,0,0,1,3,0,0,0,1,3,1,1,\"NA\",1,\"NA\",0,0,0,0,\"NA\",0,2,0,1,0,1,\"NA\",3,2,5,0,0,0,0,0,3,3,5,1,0,1,0,1,0,0,0,0,0,0,0,0,0,0,0,0,0,0,0,0,0,0,\"NA\",0,\"NA\",0,\"NA\",1,\"NA\",0,0,0,1,1,\"NA\",0,0,0,0,1,\"NA\",\"NA\",1,3,4,1,\"NA\",1,0,2,0,0,0,0,0,0,2,0,0,\"NA\",1,\"NA\",0,\"NA\",0,\"NA\",0,0,0,0,0,0,0,0,0,0,0,0,\"NA\",0,1,0,0,0,1,0,0,0,0,0,\"NA\",\"NA\",0,0,\"NA\",0,0,0,0,0,0,0,\"NA\",\"NA\",0,0,0,0,0,0,\"NA\",0,0,0,0,\"NA\",\"NA\",\"NA\",0,0,0,0,0,0,0,0,0,\"NA\",\"NA\",\"NA\",0,0,0,0,0,0,0,0,0,0,0,0,\"NA\",\"NA\",\"NA\",\"NA\",\"NA\",\"NA\",\"NA\",\"NA\",\"NA\",\"NA\",\"NA\",\"NA\",\"NA\",\"NA\",\"NA\",\"NA\",0,\"NA\",\"NA\",\"NA\",0,0,0,0,0,0,0,\"NA\",\"NA\",0,0,0,0,0,\"NA\",0,0,0,0,0,\"NA\",\"NA\",\"NA\"]},{\"type\":\"double\",\"attributes\":{\"tsp\":{\"type\":\"double\",\"attributes\":{},\"value\":[1,354,1]},\"class\":{\"type\":\"character\",\"attributes\":{},\"value\":[\"ts\"]}},\"value\":[0,0,-6.63114008e-12,0.48471673,1.48471673,1.51528327,0.51528327,0.48471673,1.96943345,2.51528327,4.90830036,9.45415018,8.57641636,5.51528327,5,5.96943345,4.09169964,4.39301709,5.09169964,4.42358364,6.51528327,4.06113309,4.42358364,6.51528327,6.48471673,\"NA\",3.32405358,4.59285101,4.96943345,5.51528327,4.03056655,3.48471673,4.48471673,\"NA\",4.12461562,3.29347996,2.03056655,0.51528327,-1.14415871e-16,0,\"NA\",0,0,0,0,0,0.48471673,0.51528327,0,0,0,\"NA\",0,0,0,0,\"NA\",\"NA\",0,0,0,0,0,0,\"NA\",\"NA\",0,0,0,\"NA\",0,0,\"NA\",0,0,\"NA\",\"NA\",0.25418825,0.7537911,1,\"NA\",\"NA\",1.25418825,1.65855409,1.51528327,2.93886691,\"NA\",\"NA\",1.44159003,0.34744934,0.96943345,2,1.51528327,0.51528327,\"NA\",0.67510567,0.18171967,0.48471673,1,1,0.51528327,0,0.96943345,1.03056655,0,1.45415018,2.03056655,1.48471673,1.51528327,1,0.51528327,0,0,0,0,\"NA\",0,\"NA\",\"NA\",0,0,0,\"NA\",0,0,\"NA\",\"NA\",0,\"NA\",0,0,0,0,0,0.48471673,1.96943345,1.54584982,0,0,0.48471673,1.96943345,2.03056655,\"NA\",1,\"NA\",0.88200258,0.24963501,0,0,\"NA\",0,0.18556469,0.96943345,1.03056655,0.48471673,0.51528327,\"NA\",0.97552373,2.14418203,2.51528327,3.45415018,2.57641636,0,0,0,0,1.45415018,3,3.96943345,3.06113309,0.51528327,0.48471673,0.51528327,0.48471673,0.51528327,0,0,0,0,0,0,0,0,0,0,0,0,0,0,0,0,\"NA\",0,\"NA\",0,\"NA\",0.12088176,\"NA\",0.76204526,0.14626437,2.86039677e-17,0,0.48471673,\"NA\",0.89986065,0.28399099,-5.72079354e-17,0,0,\"NA\",\"NA\",0.71168199,1.15907895,1.96943345,3.48471673,\"NA\",1.67426492,1.49237863,0.51528327,0.96943345,1.03056655,0,0,0,0,0,0.96943345,1.03056655,\"NA\",0.10013935,\"NA\",0.74817337,\"NA\",0.06550649,\"NA\",0.02607346,0.02171723,-3.57549596e-18,0,0,0,0,0,0,0,0,0,\"NA\",0,0.09278234,0.48471673,0.51528327,0,0,0.48471673,0.51528327,0,0,0,\"NA\",\"NA\",0,0,\"NA\",0,0,0,0,0,0,0,\"NA\",\"NA\",0,0,0,0,0,0,\"NA\",0,0,0,0,\"NA\",\"NA\",\"NA\",0,0,0,0,0,0,0,0,0,\"NA\",\"NA\",\"NA\",0,0,0,0,0,0,0,0,0,0,0,0,\"NA\",\"NA\",\"NA\",\"NA\",\"NA\",\"NA\",\"NA\",\"NA\",\"NA\",\"NA\",\"NA\",\"NA\",\"NA\",\"NA\",\"NA\",\"NA\",0,\"NA\",\"NA\",\"NA\",0,0,0,0,0,0,0,\"NA\",\"NA\",0,0,0,0,0,\"NA\",0,0,0,0,0,\"NA\",\"NA\",\"NA\"]}]}"]
